{
  "users": [
    {
      "id": 1,
      "email": "cosmo@gmail.com",
      "passwd": "asd123",
      "name": "Cosmo PM",
      "folowers": 1235,
      "folowing": 323,
      "posts": 0,
      "profileIMG": "https://i.imgur.com/NTmTX1P.jpeg"
    },
    {
      "id": 2,
      "email": "eric@gmail.com",
      "passwd": "asd1234",
      "name": "Eric Busten",
      "folowers": 5433,
      "folowing": 115,
      "posts": 0,
      "profileIMG": "https://i.imgur.com/NTmTX1P.jpeg"
    },
    {
      "email": "",
      "name": " eric@gmail.com",
      "passwd": "asd1234",
      "folowers": 0,
      "folowing": 0,
      "posts": 0,
      "profileIMG": "https://i.imgur.com/NTmTX1P.jpeg",
      "id": 3
    },
    {
      "email": "pepe@gmial.com",
      "name": "pepito lopez",
      "passwd": "asdasda",
      "folowers": 0,
      "folowing": 0,
      "posts": 0,
      "profileIMG": "https://i.imgur.com/NTmTX1P.jpeg",
      "id": 4
    },
    {
      "email": "lucas",
      "name": "lopez lucas@gmial.com",
      "passwd": "asd1a32s1d2",
      "folowers": 0,
      "folowing": 0,
      "posts": 0,
      "profileIMG": "https://i.imgur.com/NTmTX1P.jpeg",
      "id": 5
    },
    {
      "email": "maria",
      "name": "perez maria@gmial.com",
      "passwd": "4d65a4d6asd",
      "folowers": 0,
      "folowing": 0,
      "posts": 0,
      "profileIMG": "https://i.imgur.com/NTmTX1P.jpeg",
      "id": 6
    },
    {
      "email": "maria",
      "name": "perez maria@gmial.com",
      "passwd": "4d65a4d6asd",
      "folowers": 0,
      "folowing": 0,
      "posts": 0,
      "profileIMG": "https://i.imgur.com/NTmTX1P.jpeg",
      "id": 7
    },
    {
      "email": "lucia",
      "name": "perez lucia@gmal",
      "passwd": "asdasdasd",
      "folowers": 0,
      "folowing": 0,
      "posts": 0,
      "profileIMG": "https://i.imgur.com/NTmTX1P.jpeg",
      "id": 8
    }
  ],
  "posts": [
    {
      "id": 1,
      "title": "json-server",
      "author": "typicode"
    }
  ],
  "comments": [
    {
      "id": 1,
      "body": "some comment",
      "postId": 1
    }
  ],
  "profile": {
    "name": "typicode"
  }
}